odoo8_addon_purchase_order_revision-8.0.1.0.0.99.dev22-py3.8-nspkg.pth
odoo_addons/purchase_order_revision/README.rst
odoo_addons/purchase_order_revision/__init__.py
odoo_addons/purchase_order_revision/__openerp__.py
odoo_addons/purchase_order_revision/i18n/ar.po
odoo_addons/purchase_order_revision/i18n/bg.po
odoo_addons/purchase_order_revision/i18n/ca.po
odoo_addons/purchase_order_revision/i18n/cs.po
odoo_addons/purchase_order_revision/i18n/da.po
odoo_addons/purchase_order_revision/i18n/de.po
odoo_addons/purchase_order_revision/i18n/en_GB.po
odoo_addons/purchase_order_revision/i18n/es.po
odoo_addons/purchase_order_revision/i18n/es_CR.po
odoo_addons/purchase_order_revision/i18n/es_EC.po
odoo_addons/purchase_order_revision/i18n/es_ES.po
odoo_addons/purchase_order_revision/i18n/es_MX.po
odoo_addons/purchase_order_revision/i18n/es_VE.po
odoo_addons/purchase_order_revision/i18n/et.po
odoo_addons/purchase_order_revision/i18n/fi.po
odoo_addons/purchase_order_revision/i18n/fr.po
odoo_addons/purchase_order_revision/i18n/fr_CH.po
odoo_addons/purchase_order_revision/i18n/fr_FR.po
odoo_addons/purchase_order_revision/i18n/gl.po
odoo_addons/purchase_order_revision/i18n/hr.po
odoo_addons/purchase_order_revision/i18n/hr_HR.po
odoo_addons/purchase_order_revision/i18n/hu.po
odoo_addons/purchase_order_revision/i18n/id.po
odoo_addons/purchase_order_revision/i18n/it.po
odoo_addons/purchase_order_revision/i18n/ja.po
odoo_addons/purchase_order_revision/i18n/mn.po
odoo_addons/purchase_order_revision/i18n/nb.po
odoo_addons/purchase_order_revision/i18n/nl.po
odoo_addons/purchase_order_revision/i18n/nl_BE.po
odoo_addons/purchase_order_revision/i18n/nl_NL.po
odoo_addons/purchase_order_revision/i18n/pl.po
odoo_addons/purchase_order_revision/i18n/pt.po
odoo_addons/purchase_order_revision/i18n/pt_BR.po
odoo_addons/purchase_order_revision/i18n/pt_PT.po
odoo_addons/purchase_order_revision/i18n/purchase_order_revision.pot
odoo_addons/purchase_order_revision/i18n/ro.po
odoo8_addon_purchase_order_revision-8.0.1.0.0.99.dev22.dist-info/METADATA
odoo8_addon_purchase_order_revision-8.0.1.0.0.99.dev22.dist-info/WHEEL
odoo8_addon_purchase_order_revision-8.0.1.0.0.99.dev22.dist-info/namespace_packages.txt
odoo8_addon_purchase_order_revision-8.0.1.0.0.99.dev22.dist-info/top_level.txt
odoo8_addon_purchase_order_revision-8.0.1.0.0.99.dev22.dist-info/RECORD
